mcplanmanager/__init__.py
mcplanmanager/app.py
mcplanmanager/dependency_tools.py
mcplanmanager/models.py
mcplanmanager/plan_manager.py
mcplanmanager-1.2.0.dist-info/licenses/LICENSE
mcplanmanager-1.2.0.dist-info/METADATA
mcplanmanager-1.2.0.dist-info/WHEEL
mcplanmanager-1.2.0.dist-info/entry_points.txt
mcplanmanager-1.2.0.dist-info/top_level.txt
mcplanmanager-1.2.0.dist-info/RECORD
