Metadata-Version: 2.4
Name: mcplanmanager
Version: 1.2.0
Summary: AI Agent任务管理系统 - MCP服务
Author-email: Suhe <donwaydoom@gmail.com>
License: MIT License
Project-URL: Homepage, https://github.com/donway19/MCPlanManager
Project-URL: Issues, https://github.com/donway19/MCPlanManager/issues
Classifier: Development Status :: 4 - Beta
Classifier: Intended Audience :: Developers
Classifier: License :: OSI Approved :: MIT License
Classifier: Operating System :: OS Independent
Classifier: Programming Language :: Python :: 3
Classifier: Programming Language :: Python :: 3.10
Classifier: Programming Language :: Python :: 3.11
Classifier: Topic :: Software Development :: Libraries :: Python Modules
Classifier: Topic :: Scientific/Engineering :: Artificial Intelligence
Requires-Python: >=3.10
License-File: LICENSE
Requires-Dist: typing_extensions>=4.5.0
Requires-Dist: fastapi>=0.104.0
Requires-Dist: uvicorn>=0.24.0
Requires-Dist: pydantic==2.10.4
Requires-Dist: fastmcp
Provides-Extra: dev
Requires-Dist: pytest>=7.0.0; extra == "dev"
Requires-Dist: black>=23.0.0; extra == "dev"
Requires-Dist: mypy>=1.0.0; extra == "dev"
Dynamic: license-file
